realign/__init__.py
realign/claude_detector.py
realign/cli.py
realign/codex_detector.py
realign/config.py
realign/hooks.py
realign/logging_config.py
realign/mcp_server.py
realign/mcp_watcher.py
realign/redactor.py
realign/commands/__init__.py
realign/commands/auto_commit.py
realign/commands/commit.py
realign/commands/config.py
realign/commands/init.py
realign/commands/search.py
realign/commands/show.py
realign_git-0.4.7.dist-info/licenses/LICENSE
realign_git-0.4.7.dist-info/METADATA
realign_git-0.4.7.dist-info/WHEEL
realign_git-0.4.7.dist-info/entry_points.txt
realign_git-0.4.7.dist-info/top_level.txt
realign_git-0.4.7.dist-info/RECORD
