Metadata-Version: 2.4
Name: realign-git
Version: 0.4.7
Summary: Track and version AI agent chat sessions with git commits
Author: ReAlign Contributors
License: MIT
Project-URL: Homepage, https://github.com/yourusername/ReAlign
Project-URL: Repository, https://github.com/yourusername/ReAlign
Project-URL: Documentation, https://github.com/yourusername/ReAlign#readme
Project-URL: Bug Tracker, https://github.com/yourusername/ReAlign/issues
Keywords: git,ai,agent,chat,history,version-control,mcp,claude
Classifier: Development Status :: 3 - Alpha
Classifier: Intended Audience :: Developers
Classifier: Programming Language :: Python :: 3
Classifier: Programming Language :: Python :: 3.11
Classifier: Programming Language :: Python :: 3.12
Classifier: Programming Language :: Python :: 3.13
Classifier: License :: OSI Approved :: MIT License
Classifier: Operating System :: OS Independent
Classifier: Topic :: Software Development :: Version Control :: Git
Requires-Python: >=3.11
License-File: LICENSE
Requires-Dist: typer>=0.9.0
Requires-Dist: pyyaml>=6.0
Requires-Dist: rich>=13.0.0
Requires-Dist: mcp>=1.0.0
Requires-Dist: anthropic>=0.18.0
Requires-Dist: openai>=1.0.0
Requires-Dist: detect-secrets>=1.4.0
Provides-Extra: dev
Requires-Dist: pytest>=7.0.0; extra == "dev"
Requires-Dist: pytest-cov>=4.0.0; extra == "dev"
Requires-Dist: black>=23.0.0; extra == "dev"
Requires-Dist: mypy>=1.0.0; extra == "dev"
Requires-Dist: bump-my-version>=0.26.0; extra == "dev"
Dynamic: license-file
